README.rst
setup.cfg
setup.py
pylons_debugtoolbar/__init__.py
pylons_debugtoolbar/toolbar.py
pylons_debugtoolbar/utils.py
pylons_debugtoolbar.egg-info/PKG-INFO
pylons_debugtoolbar.egg-info/SOURCES.txt
pylons_debugtoolbar.egg-info/SOURCES.txt~
pylons_debugtoolbar.egg-info/dependency_links.txt
pylons_debugtoolbar.egg-info/not-zip-safe
pylons_debugtoolbar.egg-info/requires.txt
pylons_debugtoolbar.egg-info/top_level.txt
pylons_debugtoolbar/debugtoolbar_static/css/toolbar.css
pylons_debugtoolbar/debugtoolbar_static/font/FONT_LICENSE
pylons_debugtoolbar/debugtoolbar_static/font/ubuntu.ttf
pylons_debugtoolbar/debugtoolbar_static/img/back.png
pylons_debugtoolbar/debugtoolbar_static/img/back_hover.png
pylons_debugtoolbar/debugtoolbar_static/img/bg.gif
pylons_debugtoolbar/debugtoolbar_static/img/close.png
pylons_debugtoolbar/debugtoolbar_static/img/close_hover.png
pylons_debugtoolbar/debugtoolbar_static/img/console.png
pylons_debugtoolbar/debugtoolbar_static/img/desc.gif
pylons_debugtoolbar/debugtoolbar_static/img/djdt_vertical.png
pylons_debugtoolbar/debugtoolbar_static/img/headerbg.png
pylons_debugtoolbar/debugtoolbar_static/img/indicator.png
pylons_debugtoolbar/debugtoolbar_static/img/less.png
pylons_debugtoolbar/debugtoolbar_static/img/more.png
pylons_debugtoolbar/debugtoolbar_static/img/panel_bg.png
pylons_debugtoolbar/debugtoolbar_static/img/source.png
pylons_debugtoolbar/debugtoolbar_static/img/tick-red.png
pylons_debugtoolbar/debugtoolbar_static/img/tick.png
pylons_debugtoolbar/debugtoolbar_static/js/jquery-1.7.2.min.js
pylons_debugtoolbar/debugtoolbar_static/js/jquery.tablesorter.min.js
pylons_debugtoolbar/debugtoolbar_static/js/require.js
pylons_debugtoolbar/debugtoolbar_static/js/toolbar.js
pylons_debugtoolbar/panels/__init__.py
pylons_debugtoolbar/panels/cache_base.py
pylons_debugtoolbar/panels/logger.py
pylons_debugtoolbar/panels/mako_templating.py
pylons_debugtoolbar/panels/memcached_cache.py
pylons_debugtoolbar/panels/redis_cache.py
pylons_debugtoolbar/panels/request.py
pylons_debugtoolbar/panels/routes.py
pylons_debugtoolbar/panels/settings.py
pylons_debugtoolbar/panels/sqla.py
pylons_debugtoolbar/panels/timer.py
pylons_debugtoolbar/panels/versions.py
pylons_debugtoolbar/panels/templates/logger.mako
pylons_debugtoolbar/panels/templates/mako.mako
